jupyterlab_gridwidth/__init__.py
jupyterlab_gridwidth/_version.py
jupyterlab_gridwidth/splitcell_to_gridwidth.py
jupyterlab_gridwidth-0.4.3.data/data/share/jupyter/labextensions/jupyterlab-gridwidth/build_log.json
jupyterlab_gridwidth-0.4.3.data/data/share/jupyter/labextensions/jupyterlab-gridwidth/package.json
jupyterlab_gridwidth-0.4.3.data/data/share/jupyter/labextensions/jupyterlab-gridwidth/schemas/jupyterlab-gridwidth/package.json.orig
jupyterlab_gridwidth-0.4.3.data/data/share/jupyter/labextensions/jupyterlab-gridwidth/schemas/jupyterlab-gridwidth/plugin.json
jupyterlab_gridwidth-0.4.3.data/data/share/jupyter/labextensions/jupyterlab-gridwidth/static/lib_index_js.4e04db1b3d4f4d7407af.js
jupyterlab_gridwidth-0.4.3.data/data/share/jupyter/labextensions/jupyterlab-gridwidth/static/lib_index_js.4e04db1b3d4f4d7407af.js.map
jupyterlab_gridwidth-0.4.3.data/data/share/jupyter/labextensions/jupyterlab-gridwidth/static/lib_index_js.990b35638d0e302a5a09.js
jupyterlab_gridwidth-0.4.3.data/data/share/jupyter/labextensions/jupyterlab-gridwidth/static/lib_index_js.990b35638d0e302a5a09.js.map
jupyterlab_gridwidth-0.4.3.data/data/share/jupyter/labextensions/jupyterlab-gridwidth/static/lib_index_js.9cd58bc8b7c5c0b077c5.js
jupyterlab_gridwidth-0.4.3.data/data/share/jupyter/labextensions/jupyterlab-gridwidth/static/lib_index_js.9cd58bc8b7c5c0b077c5.js.map
jupyterlab_gridwidth-0.4.3.data/data/share/jupyter/labextensions/jupyterlab-gridwidth/static/lib_index_js.a07fcb4825cec710f3c1.js
jupyterlab_gridwidth-0.4.3.data/data/share/jupyter/labextensions/jupyterlab-gridwidth/static/lib_index_js.a07fcb4825cec710f3c1.js.map
jupyterlab_gridwidth-0.4.3.data/data/share/jupyter/labextensions/jupyterlab-gridwidth/static/lib_index_js.cca94bb71b9a2a47e9c9.js
jupyterlab_gridwidth-0.4.3.data/data/share/jupyter/labextensions/jupyterlab-gridwidth/static/lib_index_js.cca94bb71b9a2a47e9c9.js.map
jupyterlab_gridwidth-0.4.3.dist-info/METADATA
jupyterlab_gridwidth-0.4.3.dist-info/WHEEL
jupyterlab_gridwidth-0.4.3.dist-info/entry_points.txt
jupyterlab_gridwidth-0.4.3.dist-info/licenses/LICENSE
jupyterlab_gridwidth-0.4.3.dist-info/RECORD
