Metadata-Version: 2.3
Name: jupyterlab_gridwidth
Version: 0.4.3
Dynamic: Keywords
Summary: Jlab extension that adjusts cell width among full width, half width, 1/3, 2/3, etc. Gridwidth replaces former 'split-cell' extension in the classic notebook.
Project-URL: Homepage, https://github.com/parmentelat/jupyterlab-gridwidth
Project-URL: Bug Tracker, https://github.com/parmentelat/jupyterlab-gridwidth/issues
Project-URL: Repository, https://github.com/parmentelat/jupyterlab-gridwidth.git
Author-email: Thierry Parmentelat <thierry.parmentelat@inria.fr>
License: BSD 3-Clause License
License-File: LICENSE
Classifier: Framework :: Jupyter :: JupyterLab :: Extensions :: Prebuilt
Classifier: License :: OSI Approved :: BSD License
Classifier: Programming Language :: Python :: 3
Requires-Python: >=3.8
Requires-Dist: jupyterlab-celltagsclasses>=0.5.0
